README.md
setup.cfg
setup.py
error_counter/__init__.py
error_counter.egg-info/PKG-INFO
error_counter.egg-info/SOURCES.txt
error_counter.egg-info/dependency_links.txt
error_counter.egg-info/requires.txt
error_counter.egg-info/top_level.txt