Metadata-Version: 2.1
Name: error-counter
Version: 0.1.0
Summary: Error Counter: Count error (e.g. network error) beyond process boundary, then issue fix command when exceeded threshold.
Home-page: https://github.com/UedaTakeyuki/error-counter
Author: Takeyuki UEDA
Author-email: gde00107@nifty.com
License: MIT
Keywords: Counter,Error,Reset
Platform: UNKNOWN
Classifier: Development Status :: 4 - Beta
Classifier: Programming Language :: Python
Classifier: Topic :: Terminals
